DescriptorDOS/Analyzer.py
DescriptorDOS/BaseWorker.py
DescriptorDOS/BasicAgent.py
DescriptorDOS/Constants.py
DescriptorDOS/Displacers.py
DescriptorDOS/LAMMPSWorker.py
DescriptorDOS/MPIAgent.py
DescriptorDOS/Manager.py
DescriptorDOS/TensorCompressor.py
DescriptorDOS/YAMLParser.py
DescriptorDOS/__init__.py
descriptordos-0.1.1.dist-info/METADATA
descriptordos-0.1.1.dist-info/WHEEL
descriptordos-0.1.1.dist-info/top_level.txt
descriptordos-0.1.1.dist-info/RECORD
