Metadata-Version: 2.4
Name: DescriptorDOS
Version: 0.1.1
Summary: Score-matching the descriptor density of states for model agnostic sampling
Author-email: Thomas D Swinburne <thomas.swinburne@cnrs.fr>
License-Expression: MIT
Project-URL: Homepage, https://github.com/tomswinburne/DescriptorDOS
Project-URL: Documentation, https://github.com/tomswinburne/DescriptorDOS
Project-URL: Source, https://github.com/tomswinburne/DescriptorDOS
Requires-Python: >=3.10
Requires-Dist: numpy>=1.21
Requires-Dist: mpi4py>=3.1
Requires-Dist: matplotlib>=3.4
Requires-Dist: pyyaml>=6.0.2
Requires-Dist: lammps>=2024.8.29.0.0
Requires-Dist: scipy>1.0.0
